{
  "db_name": "PostgreSQL",
  "query": "\n            SELECT product_id\n            FROM subscriptions\n            WHERE billing_account_id = $1 AND status = 'active'\n            ",
  "describe": {
    "columns": [
      {
        "ordinal": 0,
        "name": "product_id",
        "type_info": "Varchar"
      }
    ],
    "parameters": {
      "Left": [
        "Int8"
      ]
    },
    "nullable": [
      true
    ]
  },
  "hash": "ab48d486c8cffd54fd384b33c0a74e34ed8f941ff672e40c2880b9c561aa7d2a"
}
